restage/__init__.py
restage/bifrost_choppers.py
restage/cache.py
restage/cspec_choppers.py
restage/database.py
restage/emulate.py
restage/energy.py
restage/instr.py
restage/mcpl.py
restage/run.py
restage/scan.py
restage/splitrun.py
restage/tables.py
restage/config/__init__.py
restage/config/default.yaml
restage-0.10.1.dist-info/METADATA
restage-0.10.1.dist-info/WHEEL
restage-0.10.1.dist-info/entry_points.txt
restage-0.10.1.dist-info/top_level.txt
restage-0.10.1.dist-info/RECORD
