Metadata-Version: 2.4
Name: restage
Version: 0.10.1
Author-email: Gregory Tucker <gregory.tucker@ess.eu>
License: BSD-3-Clause
Classifier: License :: OSI Approved :: BSD License
Classifier: Programming Language :: Python :: 3
Classifier: Programming Language :: Python :: 3 :: Only
Classifier: Programming Language :: Python :: 3.10
Classifier: Programming Language :: Python :: 3.11
Classifier: Programming Language :: Python :: 3.12
Classifier: Programming Language :: Python :: 3.13
Classifier: Programming Language :: Python :: 3.14
Requires-Python: >=3.9
Requires-Dist: zenlog>=1.1
Requires-Dist: platformdirs>=3.11
Requires-Dist: confuse
Requires-Dist: psutil>=5.9.6
Requires-Dist: mccode-antlr[hdf5]>=0.17.0
Provides-Extra: test
Requires-Dist: pytest; extra == "test"
Requires-Dist: chopcal>=0.4.0; extra == "test"
